med_seg_diff_pytorch/__init__.py
med_seg_diff_pytorch/dataset.py
med_seg_diff_pytorch/med_seg_diff_pytorch.py
med_seg_diff_pytorch-0.3.3.dist-info/LICENSE
med_seg_diff_pytorch-0.3.3.dist-info/METADATA
med_seg_diff_pytorch-0.3.3.dist-info/WHEEL
med_seg_diff_pytorch-0.3.3.dist-info/top_level.txt
med_seg_diff_pytorch-0.3.3.dist-info/RECORD
