Metadata-Version: 2.1
Name: med-seg-diff-pytorch
Version: 0.3.3
Summary: MedSegDiff - SOTA medical image segmentation - Pytorch
Home-page: https://github.com/lucidrains/med-seg-diff-pytorch
Author: Phil Wang
Author-email: lucidrains@gmail.com
License: MIT
Keywords: artificial intelligence,deep learning,denoising diffusion,medical segmentation
Classifier: Development Status :: 4 - Beta
Classifier: Intended Audience :: Developers
Classifier: Topic :: Scientific/Engineering :: Artificial Intelligence
Classifier: License :: OSI Approved :: MIT License
Classifier: Programming Language :: Python :: 3.6
License-File: LICENSE
Requires-Dist: beartype
Requires-Dist: einops
Requires-Dist: lion-pytorch
Requires-Dist: torch
Requires-Dist: torchvision
Requires-Dist: tqdm
Requires-Dist: accelerate >=0.25.0
Requires-Dist: wandb
